dencam/__init__.py
dencam/__main__.py
dencam/buttons.py
dencam/example_config.yaml
dencam/gui.py
dencam/logs.py
dencam/networking.py
dencam/recorder.py
dencam-0.0.3.dist-info/LICENSE
dencam-0.0.3.dist-info/METADATA
dencam-0.0.3.dist-info/WHEEL
dencam-0.0.3.dist-info/entry_points.txt
dencam-0.0.3.dist-info/top_level.txt
dencam-0.0.3.dist-info/RECORD
