Metadata-Version: 2.1
Name: dencam
Version: 0.0.3
Summary: Code for MiniDencam: Polar bear maternal den observation system.
Home-page: https://github.com/icr-ctl/dencam
Author: Conservation Technology Lab at the San Diego Zoo Wildlife Alliance
License: MIT
Platform: UNKNOWN
Classifier: Programming Language :: Python :: 3
Classifier: License :: OSI Approved :: MIT License
Classifier: Development Status :: 3 - Alpha
Classifier: Topic :: Scientific/Engineering
License-File: LICENSE
Requires-Dist: pyyaml
Requires-Dist: rpi.gpio
Requires-Dist: picamera
Requires-Dist: netifaces
